kkrobots/__init__.py
kkrobots/parse.py
kkrobots-1.0.0.dist-info/LICENSE.txt
kkrobots-1.0.0.dist-info/METADATA
kkrobots-1.0.0.dist-info/WHEEL
kkrobots-1.0.0.dist-info/top_level.txt
kkrobots-1.0.0.dist-info/RECORD
