Metadata-Version: 2.1
Name: kkrobots
Version: 1.0.0
Summary: kkrobots安全爬虫守护者
Author: Kuizi
Author-email: 123751307@qq.com
License: MIT
Classifier: Development Status :: 3 - Alpha
Classifier: Programming Language :: Python :: 3
Classifier: License :: OSI Approved :: MIT License
Classifier: Operating System :: OS Independent
Classifier: Intended Audience :: Developers
Classifier: Topic :: Utilities
Requires-Python: >=3.7
License-File: LICENSE.txt
